{"char2idx": {"<PAD>": 0, "<SOS>": 1, "<END>": 2, "<UNK>": 3, "\uc5b4\uc11c": 4, "\ubcf4\uc778\ub2e4": 5, "\uad81\uae08\ud574": 6, "\ub098": 7, "\ub098\uc624\uc138\uc694": 8, "\ud63c\uc790\ub97c": 9, "\ub2e4\uc74c": 10, "\uc2b9\uc9c4": 11, "\uc9c8\ub9b0\ub2e4": 12, "\ud3c9\uc18c\uc5d0": 13, "\ub3c8\uc740": 14, "\ub044\uace0": 15, "\ub610": 16, "\uac14\uc5b4": 17, "\uc798\uc0dd\uacbc\uc5b4": 18, "\uc9d1\ucc29\ud558\uc9c0": 19, "\uac19\uc544": 20, "\ud574": 21, "\uc6b4\ub3d9\ub9cc": 22, "\uc120\ubb3c\ub85c": 23, "\uc124\uc6c0": 24, "\ub0a8\uc790\uce5c\uad6c": 25, "\ubb50\ud558\ub294\uc9c0": 26, "\ucac4\ub531": 27, "\uc2f6\uc5b4": 28, "\uc6b4\ub3d9\uc744": 29, "\uac00\ub9cc": 30, "\uac70\uc9d3\ub9d0": 31, "\ub540\uc744": 32, "\uc5f4": 33, "\ud574\ubcf4\uc138\uc694": 34, "\uc801\ub2f9\ud788": 35, "\uc6b4\ub3d9": 36, "\uc624\ub298": 37, "\uc904\uae4c": 38, "\ub540\ub09c\ub2e4": 39, "\ub370\ub824\uac00\uace0": 40, "\ub530\ub73b\ud558\uac8c": 41, "\uc78a\uace0": 42, "\uc0ac\ub78c\ub3c4": 43, "\ucf1c\ub193\uace0": 44, "\uac00\uc2a4\ubd88": 45, "\uac78\ub9ac\uaca0\uc5b4": 46, "\ub354": 47, "\uadf8\ub7f4": 48, "\uac00\uc0c1\ud654\ud3d0": 49, "\ub54c\uae4c\uc9c0": 50, "\ub530\ub77c": 51, "\uc790\uc758": 52, "\ub098\ub77c\ub97c": 53, "\ud6c8\ud6c8\ud574": 54, "\uc548": 55, "\ub098\uac14\uc5b4": 56, "\uac00\ub09c\ud55c": 57, "\uac00\ub054\uc740": 58, "\ub108\ubb34": 59, "\ub098\uc654\ub2e4": 60, "\uc0dd\uac01\ud574\ubcf4\uc138\uc694": 61, "\ub9ce\uc774": 62, "\ube60\ub97c\uc218\ub85d": 63, "\uc0dd\uc77c\uc778\ub370": 64, "\uc88b\uc544\uc694": 65, "\uc880": 66, "\uc88b\uc744": 67, "\ubb50\uac00": 68, "\ub2e4\uc2dc": 69, "\uacb0\ub2e8\uc740": 70, "\uc9d1\uc5d0": 71, "\uac70\uc608\uc694": 72, "\ubbff\uc5b4\uc918": 73, "\ud558\uc138\uc694": 74, "\uac00\ub054": 75, "\ucf1c\uace0": 76, "\uc804\uc0dd\uc5d0": 77, "\uc124\ub4dd\ud574\ubcf4\uc138\uc694": 78, "\uac8c": 79, "\ud544\uc694\ud588\ub358": 80, "\ub9c8\uc138\uc694": 81, "\uad6c\ud558\uc168\ub098\uc694": 82, "\uac00\uc2a4\ube44": 83, "\uac19\uc544\uc694": 84, "\uadf8": 85, "\ub2ec\uc5d0\ub294": 86, "\uc0ac\uc138\uc694": 87, "\ub9dd\ud568": 88, "\ube44\uc2fc\ub370": 89, "\uc88b\ub2e4": 90, "\uc0c8\ucd9c\ubc1c": 91, "\ud63c\uc790\uc778\uac8c": 92, "\ub4e4\uc5b4\uc62c": 93, "\uc808\uc57d\ud574\ubd10\uc694": 94, "\ub3cc\uc544\uac00\uc11c": 95, "\ud568\uaed8": 96, "\uac83": 97, "\uc990\uae30\uc138\uc694": 98, "\uc88b\uc744\uae4c": 99, "\ud544\uc694\ud55c": 100, "\uc788\uc5b4\ub3c4": 101, "\uac10\uae30": 102, "\uad50\ud68c": 103, "\ub0a8\uc790\uce5c\uad6c\uac00": 104, "\ub9c8\uc74c\uc744": 105, "\ub098\uc628\uac70": 106, "\ubb58": 107, "\uc2dd\ud600\uc8fc\uc138\uc694": 108, "\ube68\ub9ac": 109, "\ubc14\ube60": 110}, "idx2char": {"0": "<PAD>", "1": "<SOS>", "2": "<END>", "3": "<UNK>", "4": "\uc5b4\uc11c", "5": "\ubcf4\uc778\ub2e4", "6": "\uad81\uae08\ud574", "7": "\ub098", "8": "\ub098\uc624\uc138\uc694", "9": "\ud63c\uc790\ub97c", "10": "\ub2e4\uc74c", "11": "\uc2b9\uc9c4", "12": "\uc9c8\ub9b0\ub2e4", "13": "\ud3c9\uc18c\uc5d0", "14": "\ub3c8\uc740", "15": "\ub044\uace0", "16": "\ub610", "17": "\uac14\uc5b4", "18": "\uc798\uc0dd\uacbc\uc5b4", "19": "\uc9d1\ucc29\ud558\uc9c0", "20": "\uac19\uc544", "21": "\ud574", "22": "\uc6b4\ub3d9\ub9cc", "23": "\uc120\ubb3c\ub85c", "24": "\uc124\uc6c0", "25": "\ub0a8\uc790\uce5c\uad6c", "26": "\ubb50\ud558\ub294\uc9c0", "27": "\ucac4\ub531", "28": "\uc2f6\uc5b4", "29": "\uc6b4\ub3d9\uc744", "30": "\uac00\ub9cc", "31": "\uac70\uc9d3\ub9d0", "32": "\ub540\uc744", "33": "\uc5f4", "34": "\ud574\ubcf4\uc138\uc694", "35": "\uc801\ub2f9\ud788", "36": "\uc6b4\ub3d9", "37": "\uc624\ub298", "38": "\uc904\uae4c", "39": "\ub540\ub09c\ub2e4", "40": "\ub370\ub824\uac00\uace0", "41": "\ub530\ub73b\ud558\uac8c", "42": "\uc78a\uace0", "43": "\uc0ac\ub78c\ub3c4", "44": "\ucf1c\ub193\uace0", "45": "\uac00\uc2a4\ubd88", "46": "\uac78\ub9ac\uaca0\uc5b4", "47": "\ub354", "48": "\uadf8\ub7f4", "49": "\uac00\uc0c1\ud654\ud3d0", "50": "\ub54c\uae4c\uc9c0", "51": "\ub530\ub77c", "52": "\uc790\uc758", "53": "\ub098\ub77c\ub97c", "54": "\ud6c8\ud6c8\ud574", "55": "\uc548", "56": "\ub098\uac14\uc5b4", "57": "\uac00\ub09c\ud55c", "58": "\uac00\ub054\uc740", "59": "\ub108\ubb34", "60": "\ub098\uc654\ub2e4", "61": "\uc0dd\uac01\ud574\ubcf4\uc138\uc694", "62": "\ub9ce\uc774", "63": "\ube60\ub97c\uc218\ub85d", "64": "\uc0dd\uc77c\uc778\ub370", "65": "\uc88b\uc544\uc694", "66": "\uc880", "67": "\uc88b\uc744", "68": "\ubb50\uac00", "69": "\ub2e4\uc2dc", "70": "\uacb0\ub2e8\uc740", "71": "\uc9d1\uc5d0", "72": "\uac70\uc608\uc694", "73": "\ubbff\uc5b4\uc918", "74": "\ud558\uc138\uc694", "75": "\uac00\ub054", "76": "\ucf1c\uace0", "77": "\uc804\uc0dd\uc5d0", "78": "\uc124\ub4dd\ud574\ubcf4\uc138\uc694", "79": "\uac8c", "80": "\ud544\uc694\ud588\ub358", "81": "\ub9c8\uc138\uc694", "82": "\uad6c\ud558\uc168\ub098\uc694", "83": "\uac00\uc2a4\ube44", "84": "\uac19\uc544\uc694", "85": "\uadf8", "86": "\ub2ec\uc5d0\ub294", "87": "\uc0ac\uc138\uc694", "88": "\ub9dd\ud568", "89": "\ube44\uc2fc\ub370", "90": "\uc88b\ub2e4", "91": "\uc0c8\ucd9c\ubc1c", "92": "\ud63c\uc790\uc778\uac8c", "93": "\ub4e4\uc5b4\uc62c", "94": "\uc808\uc57d\ud574\ubd10\uc694", "95": "\ub3cc\uc544\uac00\uc11c", "96": "\ud568\uaed8", "97": "\uac83", "98": "\uc990\uae30\uc138\uc694", "99": "\uc88b\uc744\uae4c", "100": "\ud544\uc694\ud55c", "101": "\uc788\uc5b4\ub3c4", "102": "\uac10\uae30", "103": "\uad50\ud68c", "104": "\ub0a8\uc790\uce5c\uad6c\uac00", "105": "\ub9c8\uc74c\uc744", "106": "\ub098\uc628\uac70", "107": "\ubb58", "108": "\uc2dd\ud600\uc8fc\uc138\uc694", "109": "\ube68\ub9ac", "110": "\ubc14\ube60"}, "vocab_size": 111, "pad_symbol": "<PAD>", "std_symbol": "<SOS>", "end_symbol": "<END>", "unk_symbol": "<UNK>"}